managed/__init__.py
managed/_tensor.py
managed/_utils.py
managed/device_manager.py
managed/module.py
managed/tensor.py
tensor_managed-0.1.dist-info/LICENSE
tensor_managed-0.1.dist-info/METADATA
tensor_managed-0.1.dist-info/WHEEL
tensor_managed-0.1.dist-info/top_level.txt
tensor_managed-0.1.dist-info/RECORD
